ihs_dl/__init__.py
ihs_dl/backend.py
ihs_dl-0.0.2.dist-info/LICENSE
ihs_dl-0.0.2.dist-info/METADATA
ihs_dl-0.0.2.dist-info/WHEEL
ihs_dl-0.0.2.dist-info/entry_points.txt
ihs_dl-0.0.2.dist-info/top_level.txt
ihs_dl-0.0.2.dist-info/RECORD
