Metadata-Version: 2.1
Name: ihs-dl
Version: 0.0.2
Summary: IHS Markit Teardown Photo Downloader
Home-page: UNKNOWN
Author: DerNuntius
Author-email: hugo@melder.xyz
License: GPLv3
Platform: any
Classifier: Programming Language :: Python :: 3
Classifier: License :: OSI Approved :: GNU General Public License (GPL)
Classifier: Operating System :: OS Independent
Requires-Dist: beautifulsoup4
